algorithms/__init__.py
algorithms/image_processing/__init__.py
algorithms/image_processing/cut_map.py
algorithms/image_processing/find_blue_object.py
algorithms/pathfinding/__init__.py
algorithms/pathfinding/astar.py
algorithms/pathfinding/grid_node.py
algorithms/pathfinding/utils/__init__.py
algorithms/pathfinding/utils/map_utils.py
algorithms/visualization/__init__.py
algorithms/visualization/gui.py
mdnf_algorithms-0.1.1.dist-info/METADATA
mdnf_algorithms-0.1.1.dist-info/WHEEL
mdnf_algorithms-0.1.1.dist-info/top_level.txt
mdnf_algorithms-0.1.1.dist-info/RECORD
