Metadata-Version: 2.1
Name: mdnf_algorithms
Version: 0.1.1
Summary: A dnf algorithms of the module
Author: bcy
Author-email: baochangyingi@gmail.com
Classifier: Programming Language :: Python :: 3
Classifier: License :: OSI Approved :: MIT License
Classifier: Operating System :: OS Independent
Requires-Python: >=3.6
Requires-Dist: matplotlib ==3.9.1
Requires-Dist: numpy ==1.26.4
Requires-Dist: opencv-contrib-python ==4.10.0.82
Requires-Dist: opencv-python ==4.10.0.84
Requires-Dist: Pillow ==10.4.0
Requires-Dist: setuptools ==69.5.1
